{
  "gitSyncId": "6840b6d2ece888096e42342a_5685309b-b992-4642-810f-2064085767f8",
  "id": "Resources Original_del_res_pair_soft",
  "pluginId": "mysql-plugin",
  "pluginType": "DB",
  "unpublishedAction": {
    "actionConfiguration": {
      "body": "UPDATE resource_language_pairs\nSET is_active = 0, updated_at = NOW()\nWHERE resource_id = {{ this.params.resource_id }}\n  AND source_language_id = {{ this.params.source_language_id }}\n  AND target_language_id = {{ this.params.target_language_id }};\n",
      "encodeParamsToggle": true,
      "paginationType": "NONE",
      "pluginSpecifiedTemplates": [
        {
          "value": true
        }
      ],
      "timeoutInMillisecond": 10000
    },
    "confirmBeforeExecute": false,
    "datasource": {
      "id": "linktranslation",
      "isAutoGenerated": false,
      "name": "linktranslation",
      "pluginId": "mysql-plugin"
    },
    "dynamicBindingPathList": [
      {
        "key": "body"
      }
    ],
    "name": "del_res_pair_soft",
    "pageId": "Resources Original",
    "runBehaviour": "MANUAL",
    "userSetOnLoad": false
  }
}