{
  "gitSyncId": "6840b6d2ece888096e42342a_a68848f3-7a4e-44b4-a879-0543ea500775",
  "id": "Templates_AppNav.itemsForLabel",
  "pluginId": "js-plugin",
  "pluginType": "JS",
  "unpublishedAction": {
    "actionConfiguration": {
      "encodeParamsToggle": true,
      "jsArguments": [
        {
          "name": "lbl"
        }
      ],
      "paginationType": "NONE",
      "timeoutInMillisecond": 10000
    },
    "collectionId": "Templates_AppNav",
    "confirmBeforeExecute": false,
    "datasource": {
      "isAutoGenerated": false,
      "name": "UNUSED_DATASOURCE",
      "pluginId": "js-plugin"
    },
    "dynamicBindingPathList": [
      {
        "key": "body"
      }
    ],
    "fullyQualifiedName": "AppNav.itemsForLabel",
    "name": "itemsForLabel",
    "pageId": "Templates",
    "runBehaviour": "MANUAL",
    "userSetOnLoad": false
  }
}