{
  "gitSyncId": "6840b6d2ece888096e42342a_174a9916-d2c0-4a50-9358-558c801e7b0a",
  "id": "Customer Portals_ins_portal",
  "pluginId": "mysql-plugin",
  "pluginType": "DB",
  "unpublishedAction": {
    "actionConfiguration": {
      "body": "INSERT INTO customer_portals (\n  customer_portal_name,\n  customer_id,\n  customer_contact_id,\n  customer_portal_credentials,\n  customer_portal_website,\n  customer_portal_notes,\n  customer_portal_status,\n  portal_scope,\n  customer_portal_first_update,\n  customer_portal_last_update,\n  customer_portal_next_update\n) VALUES (\n  {{ jf_port_ins.formData.customer_portal_name ?? null }},\n  {{ jf_port_ins.formData.customer_id ?? null }},\n  {{ jf_port_ins.formData.customer_contact_id ?? null }},\n  {{ jf_port_ins.formData.customer_portal_credentials ?? null }},\n  {{ jf_port_ins.formData.customer_portal_website ?? null }},\n  {{ jf_port_ins.formData.customer_portal_notes ?? null }},\n  COALESCE(NULLIF({{ jf_port_ins.formData.customer_portal_status }}, ''), 'Active'),\n  COALESCE(NULLIF({{ jf_port_ins.formData.portal_scope }}, ''), 'Projects'),\n  {{ jf_port_ins.formData.customer_portal_first_update ?? null }},\n  {{ jf_port_ins.formData.customer_portal_last_update ?? null }},\n  {{ jf_port_ins.formData.customer_portal_next_update ?? null }}\n);\n",
      "encodeParamsToggle": true,
      "paginationType": "NONE",
      "pluginSpecifiedTemplates": [
        {
          "value": true
        }
      ],
      "timeoutInMillisecond": 10000
    },
    "confirmBeforeExecute": false,
    "datasource": {
      "id": "linktranslation",
      "isAutoGenerated": false,
      "name": "linktranslation",
      "pluginId": "mysql-plugin"
    },
    "dynamicBindingPathList": [
      {
        "key": "body"
      }
    ],
    "name": "ins_portal",
    "pageId": "Customer Portals",
    "runBehaviour": "MANUAL",
    "userSetOnLoad": false
  }
}