{
  "animateLoading": true,
  "borderRadius": "{{appsmith.theme.borderRadius.appBorderRadius}}",
  "bottomRow": 6,
  "dynamicBindingPathList": [
    {
      "key": "truncateButtonColor"
    },
    {
      "key": "fontFamily"
    },
    {
      "key": "borderRadius"
    }
  ],
  "dynamicHeight": "AUTO_HEIGHT",
  "dynamicTriggerPathList": [],
  "fontFamily": "{{appsmith.theme.fontFamily.appFont}}",
  "fontSize": "1.25rem",
  "fontStyle": "BOLD",
  "isLoading": false,
  "isVisible": true,
  "key": "5ata48qdia",
  "leftColumn": 45,
  "maxDynamicHeight": 9000,
  "minDynamicHeight": 4,
  "minWidth": 450,
  "mobileBottomRow": 63,
  "mobileLeftColumn": 1,
  "mobileRightColumn": 17,
  "mobileTopRow": 59,
  "needsErrorInfo": false,
  "originalBottomRow": 7,
  "originalTopRow": 2,
  "overflow": "NONE",
  "parentColumnSpace": 25.1875,
  "parentId": "rzdzrbc4as",
  "parentRowSpace": 10,
  "renderMode": "CANVAS",
  "responsiveBehavior": "fill",
  "rightColumn": 61,
  "shouldTruncate": false,
  "text": "Price List Items",
  "textAlign": "LEFT",
  "textColor": "#14532d",
  "topRow": 2,
  "truncateButtonColor": "{{appsmith.theme.colors.primaryColor}}",
  "type": "TEXT_WIDGET",
  "version": 1,
  "widgetId": "zzajes3sw3",
  "widgetName": "Price_List_ItemsCopy"
}