{
  "gitSyncId": "6840b6d2ece888096e42342a_c8e6aaaa-f961-47ef-9c95-eac247ba016f",
  "id": "Resources Original_check_username_exists",
  "pluginId": "mysql-plugin",
  "pluginType": "DB",
  "unpublishedAction": {
    "actionConfiguration": {
      "body": "SELECT COUNT(*) AS cnt\nFROM resources\nWHERE resource_username = {{ this.params.username }}\n  AND resource_id <> {{ this.params.resource_id }};\n",
      "encodeParamsToggle": true,
      "paginationType": "NONE",
      "pluginSpecifiedTemplates": [
        {
          "value": true
        }
      ],
      "timeoutInMillisecond": 10000
    },
    "confirmBeforeExecute": false,
    "datasource": {
      "id": "linktranslation",
      "isAutoGenerated": false,
      "name": "linktranslation",
      "pluginId": "mysql-plugin"
    },
    "dynamicBindingPathList": [
      {
        "key": "body"
      }
    ],
    "name": "check_username_exists",
    "pageId": "Resources Original",
    "runBehaviour": "MANUAL",
    "userSetOnLoad": false
  }
}