{
  "gitSyncId": "6840b6d2ece888096e42342a_0beae33c-c523-4cc8-b11a-09de4e9a0453",
  "id": "Login Page_auth_login_sha2",
  "pluginId": "mysql-plugin",
  "pluginType": "DB",
  "unpublishedAction": {
    "actionConfiguration": {
      "body": "SELECT\n  r.resource_id,\n  r.resource_username,\n  r.resource_full_name,\n  r.resource_email,\n  r.role_id,\n  r.resource_is_active\nFROM resources r\nWHERE r.resource_username = {{ i_username.text }}\n  AND r.resource_is_active = 1\n  AND r.resource_password_hash = SHA2({{ i_password.text }}, 256)\nLIMIT 1;\n",
      "encodeParamsToggle": true,
      "paginationType": "NONE",
      "pluginSpecifiedTemplates": [
        {
          "value": true
        }
      ],
      "timeoutInMillisecond": 10000
    },
    "confirmBeforeExecute": false,
    "datasource": {
      "id": "linktranslation",
      "isAutoGenerated": false,
      "name": "linktranslation",
      "pluginId": "mysql-plugin"
    },
    "dynamicBindingPathList": [
      {
        "key": "body"
      }
    ],
    "name": "auth_login_sha2",
    "pageId": "Login Page",
    "runBehaviour": "MANUAL",
    "userSetOnLoad": false
  }
}