{
  "accentColor": "{{appsmith.theme.colors.primaryColor}}",
  "allowAddNewRow": false,
  "animateLoading": true,
  "borderColor": "#E0DEDE",
  "borderRadius": "0px",
  "borderWidth": "1",
  "bottomRow": 144,
  "bottomRowBeforeCollapse": 158,
  "boxShadow": "0 1px 3px 0 rgba(0, 0, 0, 0.1), 0 1px 2px 0 rgba(0, 0, 0, 0.06)",
  "cachedTableData": {},
  "canFreezeColumn": true,
  "childStylesheet": {
    "button": {
      "borderRadius": "{{appsmith.theme.borderRadius.appBorderRadius}}",
      "boxShadow": "none",
      "buttonColor": "{{appsmith.theme.colors.primaryColor}}"
    },
    "editActions": {
      "discardBorderRadius": "{{appsmith.theme.borderRadius.appBorderRadius}}",
      "discardButtonColor": "{{appsmith.theme.colors.primaryColor}}",
      "saveBorderRadius": "{{appsmith.theme.borderRadius.appBorderRadius}}",
      "saveButtonColor": "{{appsmith.theme.colors.primaryColor}}"
    },
    "iconButton": {
      "borderRadius": "{{appsmith.theme.borderRadius.appBorderRadius}}",
      "boxShadow": "none",
      "buttonColor": "{{appsmith.theme.colors.primaryColor}}"
    },
    "menuButton": {
      "borderRadius": "{{appsmith.theme.borderRadius.appBorderRadius}}",
      "boxShadow": "none",
      "menuColor": "{{appsmith.theme.colors.primaryColor}}"
    }
  },
  "columnOrder": [
    "company_id",
    "company_name",
    "logo",
    "website",
    "signature",
    "address",
    "currency_id",
    "tax_number",
    "bank_account",
    "payoneer_account",
    "created_at",
    "updated_at",
    "currency_name",
    "EditActions1"
  ],
  "columnUpdatedAt": 1755206592525,
  "columnWidthMap": {},
  "compactMode": "DEFAULT",
  "customIsLoading": false,
  "customIsLoadingValue": "",
  "defaultPageSize": 0,
  "defaultSelectedRowIndex": 0,
  "defaultSelectedRowIndices": [
    0
  ],
  "delimiter": ",",
  "dynamicBindingPathList": [
    {
      "key": "accentColor"
    },
    {
      "key": "tableData"
    },
    {
      "key": "totalRecordsCount"
    },
    {
      "key": "primaryColumns.company_id.computedValue"
    },
    {
      "key": "primaryColumns.company_name.computedValue"
    },
    {
      "key": "primaryColumns.logo.computedValue"
    },
    {
      "key": "primaryColumns.website.computedValue"
    },
    {
      "key": "primaryColumns.signature.computedValue"
    },
    {
      "key": "primaryColumns.address.computedValue"
    },
    {
      "key": "primaryColumns.currency_id.computedValue"
    },
    {
      "key": "primaryColumns.tax_number.computedValue"
    },
    {
      "key": "primaryColumns.bank_account.computedValue"
    },
    {
      "key": "primaryColumns.payoneer_account.computedValue"
    },
    {
      "key": "primaryColumns.created_at.computedValue"
    },
    {
      "key": "primaryColumns.updated_at.computedValue"
    },
    {
      "key": "primaryColumns.EditActions1.saveButtonColor"
    },
    {
      "key": "primaryColumns.EditActions1.saveBorderRadius"
    },
    {
      "key": "primaryColumns.EditActions1.discardBorderRadius"
    },
    {
      "key": "primaryColumns.EditActions1.isSaveDisabled"
    },
    {
      "key": "primaryColumns.EditActions1.isDiscardDisabled"
    },
    {
      "key": "primaryColumns.currency_name.computedValue"
    }
  ],
  "dynamicPropertyPathList": [
    {
      "key": "tableData"
    },
    {
      "key": "primaryColumns.EditActions1.isSaveDisabled"
    },
    {
      "key": "primaryColumns.EditActions1.isDiscardDisabled"
    },
    {
      "key": "onRowSelected"
    }
  ],
  "dynamicTriggerPathList": [
    {
      "key": "onPageChange"
    },
    {
      "key": "onSearchTextChanged"
    },
    {
      "key": "onSort"
    },
    {
      "key": "onAddNewRowSave"
    },
    {
      "key": "primaryColumns.EditActions1.onSave"
    },
    {
      "key": "onRowSelected"
    }
  ],
  "enableClientSideSearch": false,
  "endOfData": false,
  "flexVerticalAlignment": "start",
  "horizontalAlignment": "LEFT",
  "inlineEditingSaveOption": "ROW_LEVEL",
  "isLoading": false,
  "isSortable": false,
  "isVisible": false,
  "isVisibleDownload": false,
  "isVisibleFilters": false,
  "isVisiblePagination": false,
  "isVisibleSearch": false,
  "key": "f3w2sc5acn",
  "label": "Data",
  "leftColumn": 3,
  "minWidth": 450,
  "mobileBottomRow": 42,
  "mobileLeftColumn": 6,
  "mobileRightColumn": 40,
  "mobileTopRow": 14,
  "needsErrorInfo": false,
  "onAddNewRowSave": "{{Insert_company1.run(() => {\n            showAlert(\"Successfully created!\");\n            Select_company1.run()\n          }, () => {\n            showAlert(\"Unable to create!\");\n          })}}",
  "onPageChange": "{{\n            Select_company1.run();\n            Total_record_company1.run()\n          }}",
  "onRowSelected": "{{\n  CompanyStore.setRow(currentRow);\n  resetWidget('j_edit_company', true);\n  showModal('Edit_Company_Modal');\n}}\n",
  "onSearchTextChanged": "{{\n            Select_company1.run();\n            Total_record_company1.run()\n          }}",
  "onSort": "{{\n            Select_company1.run();\n            Total_record_company1.run()\n          }}",
  "originalBottomRow": 144,
  "originalTopRow": 127,
  "parentColumnSpace": 17.9375,
  "parentId": "0",
  "parentRowSpace": 10,
  "primaryColumnId": "company_id",
  "primaryColumns": {
    "EditActions1": {
      "alias": "EditActions1",
      "allowCellWrapping": false,
      "allowSameOptionsInNewRow": true,
      "buttonStyle": "rgb(3, 179, 101)",
      "columnType": "editActions",
      "computedValue": "",
      "currencyCode": "USD",
      "decimals": 0,
      "discardActionLabel": "Discard",
      "discardBorderRadius": "{{company_table.processedTableData.map((currentRow, currentIndex) => ( (appsmith.theme.borderRadius.appBorderRadius)))}}",
      "discardButtonColor": "#F22B2B",
      "discardButtonVariant": "TERTIARY",
      "discardIconAlign": "left",
      "enableFilter": true,
      "enableSort": true,
      "horizontalAlignment": "LEFT",
      "id": "EditActions1",
      "index": 10,
      "isCellEditable": false,
      "isCellVisible": true,
      "isDerived": true,
      "isDisabled": false,
      "isDiscardDisabled": "{{company_table.processedTableData.map((currentRow, currentIndex) => ( !company_table.updatedRowIndices.includes(currentIndex)))}}",
      "isDiscardVisible": false,
      "isEditable": false,
      "isSaveDisabled": "{{company_table.processedTableData.map((currentRow, currentIndex) => ( !company_table.updatedRowIndices.includes(currentIndex)))}}",
      "isSaveVisible": false,
      "isVisible": false,
      "label": "Save / Discard",
      "notation": "standard",
      "onSave": "{{Update_company1.run(() => {\n            showAlert(\"Successfully saved!\");\n            Select_company1.run()\n          }, () => {\n            showAlert(\"Unable to save!\");\n          })}}",
      "originalId": "EditActions1",
      "saveActionLabel": "Save",
      "saveBorderRadius": "{{company_table.processedTableData.map((currentRow, currentIndex) => ( (appsmith.theme.borderRadius.appBorderRadius)))}}",
      "saveButtonColor": "{{company_table.processedTableData.map((currentRow, currentIndex) => ( (appsmith.theme.colors.primaryColor)))}}",
      "saveIconAlign": "left",
      "sticky": "right",
      "textSize": "1rem",
      "thousandSeparator": true,
      "validation": {},
      "verticalAlignment": "CENTER",
      "width": 150
    },
    "address": {
      "alias": "address",
      "allowCellWrapping": false,
      "allowSameOptionsInNewRow": true,
      "columnType": "text",
      "computedValue": "{{(() => { const tableData = company_table.processedTableData || []; return tableData.length > 0 ? tableData.map((currentRow, currentIndex) => (currentRow[\"address\"])) : address })()}}",
      "currencyCode": "USD",
      "decimals": 0,
      "enableFilter": true,
      "enableSort": true,
      "horizontalAlignment": "LEFT",
      "id": "address",
      "index": 5,
      "isCellEditable": true,
      "isCellVisible": true,
      "isDerived": false,
      "isDisabled": false,
      "isDiscardVisible": true,
      "isEditable": true,
      "isSaveVisible": true,
      "isVisible": true,
      "label": "address",
      "notation": "standard",
      "originalId": "address",
      "sticky": "",
      "textSize": "1rem",
      "thousandSeparator": true,
      "validation": {},
      "verticalAlignment": "CENTER",
      "width": 150
    },
    "bank_account": {
      "alias": "bank_account",
      "allowCellWrapping": false,
      "allowSameOptionsInNewRow": true,
      "columnType": "text",
      "computedValue": "{{(() => { const tableData = company_table.processedTableData || []; return tableData.length > 0 ? tableData.map((currentRow, currentIndex) => (currentRow[\"bank_account\"])) : bank_account })()}}",
      "currencyCode": "USD",
      "decimals": 0,
      "enableFilter": true,
      "enableSort": true,
      "horizontalAlignment": "LEFT",
      "id": "bank_account",
      "index": 8,
      "isCellEditable": true,
      "isCellVisible": true,
      "isDerived": false,
      "isDisabled": false,
      "isDiscardVisible": true,
      "isEditable": true,
      "isSaveVisible": true,
      "isVisible": true,
      "label": "bank_account",
      "notation": "standard",
      "originalId": "bank_account",
      "sticky": "",
      "textSize": "1rem",
      "thousandSeparator": true,
      "validation": {},
      "verticalAlignment": "CENTER",
      "width": 150
    },
    "company_id": {
      "alias": "company_id",
      "allowCellWrapping": false,
      "allowSameOptionsInNewRow": true,
      "columnType": "number",
      "computedValue": "{{(() => { const tableData = company_table.processedTableData || []; return tableData.length > 0 ? tableData.map((currentRow, currentIndex) => (currentRow[\"company_id\"])) : company_id })()}}",
      "currencyCode": "USD",
      "decimals": 0,
      "enableFilter": true,
      "enableSort": true,
      "horizontalAlignment": "LEFT",
      "id": "company_id",
      "index": 0,
      "isCellEditable": false,
      "isCellVisible": true,
      "isDerived": false,
      "isDisabled": false,
      "isDiscardVisible": true,
      "isEditable": false,
      "isSaveVisible": true,
      "isVisible": true,
      "label": "company_id",
      "notation": "standard",
      "originalId": "company_id",
      "sticky": "",
      "textSize": "1rem",
      "thousandSeparator": true,
      "validation": {},
      "verticalAlignment": "CENTER",
      "width": 150
    },
    "company_name": {
      "alias": "company_name",
      "allowCellWrapping": false,
      "allowSameOptionsInNewRow": true,
      "columnType": "text",
      "computedValue": "{{(() => { const tableData = company_table.processedTableData || []; return tableData.length > 0 ? tableData.map((currentRow, currentIndex) => (currentRow[\"company_name\"])) : company_name })()}}",
      "currencyCode": "USD",
      "decimals": 0,
      "enableFilter": true,
      "enableSort": true,
      "horizontalAlignment": "LEFT",
      "id": "company_name",
      "index": 1,
      "isCellEditable": true,
      "isCellVisible": true,
      "isDerived": false,
      "isDisabled": false,
      "isDiscardVisible": true,
      "isEditable": true,
      "isSaveVisible": true,
      "isVisible": true,
      "label": "company_name",
      "notation": "standard",
      "originalId": "company_name",
      "sticky": "",
      "textSize": "1rem",
      "thousandSeparator": true,
      "validation": {},
      "verticalAlignment": "CENTER",
      "width": 150
    },
    "created_at": {
      "alias": "created_at",
      "allowCellWrapping": false,
      "allowSameOptionsInNewRow": true,
      "columnType": "text",
      "computedValue": "{{(() => { const tableData = company_table.processedTableData || []; return tableData.length > 0 ? tableData.map((currentRow, currentIndex) => (currentRow[\"created_at\"])) : created_at })()}}",
      "currencyCode": "USD",
      "decimals": 0,
      "enableFilter": true,
      "enableSort": true,
      "horizontalAlignment": "LEFT",
      "id": "created_at",
      "index": 10,
      "isCellEditable": true,
      "isCellVisible": true,
      "isDerived": false,
      "isDisabled": false,
      "isDiscardVisible": true,
      "isEditable": true,
      "isSaveVisible": true,
      "isVisible": true,
      "label": "created_at",
      "notation": "standard",
      "originalId": "created_at",
      "sticky": "",
      "textSize": "1rem",
      "thousandSeparator": true,
      "validation": {},
      "verticalAlignment": "CENTER",
      "width": 150
    },
    "currency_id": {
      "alias": "currency_id",
      "allowCellWrapping": false,
      "allowSameOptionsInNewRow": true,
      "columnType": "text",
      "computedValue": "{{(() => { const tableData = company_table.processedTableData || []; return tableData.length > 0 ? tableData.map((currentRow, currentIndex) => (currentRow[\"currency_id\"])) : currency_id })()}}",
      "currencyCode": "USD",
      "decimals": 0,
      "enableFilter": true,
      "enableSort": true,
      "horizontalAlignment": "LEFT",
      "id": "currency_id",
      "index": 6,
      "isCellEditable": true,
      "isCellVisible": true,
      "isDerived": false,
      "isDisabled": false,
      "isDiscardVisible": true,
      "isEditable": true,
      "isSaveVisible": true,
      "isVisible": true,
      "label": "currency_id",
      "notation": "standard",
      "originalId": "currency_id",
      "sticky": "",
      "textSize": "1rem",
      "thousandSeparator": true,
      "validation": {},
      "verticalAlignment": "CENTER",
      "width": 150
    },
    "currency_name": {
      "alias": "currency_name",
      "allowCellWrapping": false,
      "allowSameOptionsInNewRow": true,
      "cellBackground": "",
      "columnType": "text",
      "computedValue": "{{(() => { const tableData = company_table.processedTableData || []; return tableData.length > 0 ? tableData.map((currentRow, currentIndex) => (currentRow[\"currency_name\"])) : currency_name })()}}",
      "currencyCode": "USD",
      "decimals": 0,
      "enableFilter": true,
      "enableSort": true,
      "fontStyle": "",
      "horizontalAlignment": "LEFT",
      "id": "currency_name",
      "index": 12,
      "isCellEditable": false,
      "isCellVisible": true,
      "isDerived": false,
      "isDisabled": false,
      "isDiscardVisible": true,
      "isEditable": false,
      "isSaveVisible": true,
      "isVisible": true,
      "label": "currency_name",
      "notation": "standard",
      "originalId": "currency_name",
      "sticky": "",
      "textColor": "",
      "textSize": "1rem",
      "thousandSeparator": true,
      "validation": {},
      "verticalAlignment": "CENTER",
      "width": 150
    },
    "logo": {
      "alias": "logo",
      "allowCellWrapping": false,
      "allowSameOptionsInNewRow": true,
      "columnType": "text",
      "computedValue": "{{(() => { const tableData = company_table.processedTableData || []; return tableData.length > 0 ? tableData.map((currentRow, currentIndex) => (currentRow[\"logo\"])) : logo })()}}",
      "currencyCode": "USD",
      "decimals": 0,
      "enableFilter": true,
      "enableSort": true,
      "horizontalAlignment": "LEFT",
      "id": "logo",
      "index": 2,
      "isCellEditable": true,
      "isCellVisible": true,
      "isDerived": false,
      "isDisabled": false,
      "isDiscardVisible": true,
      "isEditable": true,
      "isSaveVisible": true,
      "isVisible": true,
      "label": "logo",
      "notation": "standard",
      "originalId": "logo",
      "sticky": "",
      "textSize": "1rem",
      "thousandSeparator": true,
      "validation": {},
      "verticalAlignment": "CENTER",
      "width": 150
    },
    "payoneer_account": {
      "alias": "payoneer_account",
      "allowCellWrapping": false,
      "allowSameOptionsInNewRow": true,
      "columnType": "text",
      "computedValue": "{{(() => { const tableData = company_table.processedTableData || []; return tableData.length > 0 ? tableData.map((currentRow, currentIndex) => (currentRow[\"payoneer_account\"])) : payoneer_account })()}}",
      "currencyCode": "USD",
      "decimals": 0,
      "enableFilter": true,
      "enableSort": true,
      "horizontalAlignment": "LEFT",
      "id": "payoneer_account",
      "index": 9,
      "isCellEditable": true,
      "isCellVisible": true,
      "isDerived": false,
      "isDisabled": false,
      "isDiscardVisible": true,
      "isEditable": true,
      "isSaveVisible": true,
      "isVisible": true,
      "label": "payoneer_account",
      "notation": "standard",
      "originalId": "payoneer_account",
      "sticky": "",
      "textSize": "1rem",
      "thousandSeparator": true,
      "validation": {},
      "verticalAlignment": "CENTER",
      "width": 150
    },
    "signature": {
      "alias": "signature",
      "allowCellWrapping": false,
      "allowSameOptionsInNewRow": true,
      "columnType": "text",
      "computedValue": "{{(() => { const tableData = company_table.processedTableData || []; return tableData.length > 0 ? tableData.map((currentRow, currentIndex) => (currentRow[\"signature\"])) : signature })()}}",
      "currencyCode": "USD",
      "decimals": 0,
      "enableFilter": true,
      "enableSort": true,
      "horizontalAlignment": "LEFT",
      "id": "signature",
      "index": 4,
      "isCellEditable": true,
      "isCellVisible": true,
      "isDerived": false,
      "isDisabled": false,
      "isDiscardVisible": true,
      "isEditable": true,
      "isSaveVisible": true,
      "isVisible": true,
      "label": "signature",
      "notation": "standard",
      "originalId": "signature",
      "sticky": "",
      "textSize": "1rem",
      "thousandSeparator": true,
      "validation": {},
      "verticalAlignment": "CENTER",
      "width": 150
    },
    "tax_number": {
      "alias": "tax_number",
      "allowCellWrapping": false,
      "allowSameOptionsInNewRow": true,
      "columnType": "text",
      "computedValue": "{{(() => { const tableData = company_table.processedTableData || []; return tableData.length > 0 ? tableData.map((currentRow, currentIndex) => (currentRow[\"tax_number\"])) : tax_number })()}}",
      "currencyCode": "USD",
      "decimals": 0,
      "enableFilter": true,
      "enableSort": true,
      "horizontalAlignment": "LEFT",
      "id": "tax_number",
      "index": 7,
      "isCellEditable": true,
      "isCellVisible": true,
      "isDerived": false,
      "isDisabled": false,
      "isDiscardVisible": true,
      "isEditable": true,
      "isSaveVisible": true,
      "isVisible": true,
      "label": "tax_number",
      "notation": "standard",
      "originalId": "tax_number",
      "sticky": "",
      "textSize": "1rem",
      "thousandSeparator": true,
      "validation": {},
      "verticalAlignment": "CENTER",
      "width": 150
    },
    "updated_at": {
      "alias": "updated_at",
      "allowCellWrapping": false,
      "allowSameOptionsInNewRow": true,
      "columnType": "text",
      "computedValue": "{{(() => { const tableData = company_table.processedTableData || []; return tableData.length > 0 ? tableData.map((currentRow, currentIndex) => (currentRow[\"updated_at\"])) : updated_at })()}}",
      "currencyCode": "USD",
      "decimals": 0,
      "enableFilter": true,
      "enableSort": true,
      "horizontalAlignment": "LEFT",
      "id": "updated_at",
      "index": 11,
      "isCellEditable": true,
      "isCellVisible": true,
      "isDerived": false,
      "isDisabled": false,
      "isDiscardVisible": true,
      "isEditable": true,
      "isSaveVisible": true,
      "isVisible": true,
      "label": "updated_at",
      "notation": "standard",
      "originalId": "updated_at",
      "sticky": "",
      "textSize": "1rem",
      "thousandSeparator": true,
      "validation": {},
      "verticalAlignment": "CENTER",
      "width": 150
    },
    "website": {
      "alias": "website",
      "allowCellWrapping": false,
      "allowSameOptionsInNewRow": true,
      "columnType": "text",
      "computedValue": "{{(() => { const tableData = company_table.processedTableData || []; return tableData.length > 0 ? tableData.map((currentRow, currentIndex) => (currentRow[\"website\"])) : website })()}}",
      "currencyCode": "USD",
      "decimals": 0,
      "enableFilter": true,
      "enableSort": true,
      "horizontalAlignment": "LEFT",
      "id": "website",
      "index": 3,
      "isCellEditable": true,
      "isCellVisible": true,
      "isDerived": false,
      "isDisabled": false,
      "isDiscardVisible": true,
      "isEditable": true,
      "isSaveVisible": true,
      "isVisible": true,
      "label": "website",
      "notation": "standard",
      "originalId": "website",
      "sticky": "",
      "textSize": "1rem",
      "thousandSeparator": true,
      "validation": {},
      "verticalAlignment": "CENTER",
      "width": 150
    }
  },
  "renderMode": "CANVAS",
  "responsiveBehavior": "fill",
  "rightColumn": 58,
  "searchKey": "",
  "serverSidePaginationEnabled": false,
  "showInlineEditingOptionDropdown": true,
  "tableData": "{{ get_company.data}}",
  "textSize": "1rem",
  "topRow": 127,
  "topRowBeforeCollapse": 141,
  "totalRecordsCount": "{{Total_record_company1.data[0].count}}",
  "type": "TABLE_WIDGET_V2",
  "variant": "VARIANT2",
  "version": 2,
  "verticalAlignment": "CENTER",
  "widgetId": "4iwjhwp8fv",
  "widgetName": "company_table"
}