{
  "gitSyncId": "6840b6d2ece888096e42342a_348d636a-d74a-4948-a4e5-46472c843e9a",
  "id": "Templates_get_templates",
  "pluginId": "mysql-plugin",
  "pluginType": "DB",
  "unpublishedAction": {
    "actionConfiguration": {
      "body": "SELECT\n  t.template_id,\n  t.template_name,\n  t.template_type,\n  t.template_email_subject,\n  t.template_email_body_html,\n  t.template_email_to_field,\n  t.template_email_bcc_field,\n  t.template_from_field,\n  t.template_signature_field,\n  t.template_description,\n  t.template_version,\n  t.template_vars,\n  t.template_is_active,\n  t.created_at,\n  t.updated_at\nFROM templates t\nORDER BY t.updated_at DESC;\n",
      "encodeParamsToggle": true,
      "paginationType": "NONE",
      "pluginSpecifiedTemplates": [
        {
          "value": true
        }
      ],
      "timeoutInMillisecond": 10000
    },
    "confirmBeforeExecute": false,
    "datasource": {
      "id": "linktranslation",
      "isAutoGenerated": false,
      "name": "linktranslation",
      "pluginId": "mysql-plugin"
    },
    "dynamicBindingPathList": [],
    "name": "get_templates",
    "pageId": "Templates",
    "runBehaviour": "ON_PAGE_LOAD",
    "userSetOnLoad": true
  }
}