{
  "gitSyncId": "6840b6d2ece888096e42342a_d688fe80-e366-4370-b64e-b1bfdca7f8f1",
  "id": "Resources_AppNav.itemsFor",
  "pluginId": "js-plugin",
  "pluginType": "JS",
  "unpublishedAction": {
    "actionConfiguration": {
      "encodeParamsToggle": true,
      "jsArguments": [
        {
          "name": "col_id"
        }
      ],
      "paginationType": "NONE",
      "timeoutInMillisecond": 10000
    },
    "collectionId": "Resources_AppNav",
    "confirmBeforeExecute": false,
    "datasource": {
      "isAutoGenerated": false,
      "name": "UNUSED_DATASOURCE",
      "pluginId": "js-plugin"
    },
    "dynamicBindingPathList": [
      {
        "key": "body"
      }
    ],
    "fullyQualifiedName": "AppNav.itemsFor",
    "name": "itemsFor",
    "pageId": "Resources",
    "runBehaviour": "MANUAL",
    "userSetOnLoad": false
  }
}