{
  "gitSyncId": "6840b6d2ece888096e42342a_41a32393-966b-4707-87cf-f29c0e61407b",
  "id": "Roles and Permissions_RoleHandlers.openAssignRole",
  "pluginId": "js-plugin",
  "pluginType": "JS",
  "unpublishedAction": {
    "actionConfiguration": {
      "encodeParamsToggle": true,
      "jsArguments": [],
      "paginationType": "NONE",
      "timeoutInMillisecond": 10000
    },
    "collectionId": "Roles and Permissions_RoleHandlers",
    "confirmBeforeExecute": false,
    "datasource": {
      "isAutoGenerated": false,
      "name": "UNUSED_DATASOURCE",
      "pluginId": "js-plugin"
    },
    "dynamicBindingPathList": [
      {
        "key": "body"
      }
    ],
    "fullyQualifiedName": "RoleHandlers.openAssignRole",
    "name": "openAssignRole",
    "pageId": "Roles and Permissions",
    "runBehaviour": "MANUAL",
    "userSetOnLoad": false
  }
}