{
  "gitSyncId": "6840b6d2ece888096e42342a_8a0b5100-1ddc-41be-9a43-96a2aac7cae3",
  "id": "Price List_get_bm_cur_dd",
  "pluginId": "mysql-plugin",
  "pluginType": "DB",
  "unpublishedAction": {
    "actionConfiguration": {
      "body": "SELECT\n  cur.currency_id AS value,\n  CONCAT(cur.currency_acronym, ' - ', cur.currency_name) AS label\nFROM currencies cur\nORDER BY cur.currency_acronym, cur.currency_name\n",
      "encodeParamsToggle": true,
      "paginationType": "NONE",
      "pluginSpecifiedTemplates": [
        {
          "value": true
        }
      ],
      "timeoutInMillisecond": 10000
    },
    "confirmBeforeExecute": false,
    "datasource": {
      "id": "linktranslation",
      "isAutoGenerated": false,
      "name": "linktranslation",
      "pluginId": "mysql-plugin"
    },
    "dynamicBindingPathList": [],
    "name": "get_bm_cur_dd",
    "pageId": "Price List",
    "runBehaviour": "AUTOMATIC",
    "userSetOnLoad": false
  }
}