{
  "gitSyncId": "6840b6d2ece888096e42342a_731d2070-77a7-490d-b921-4e4b8c4cb2a9",
  "id": "Company Documentation_ISOTags.refresh",
  "pluginId": "js-plugin",
  "pluginType": "JS",
  "unpublishedAction": {
    "actionConfiguration": {
      "encodeParamsToggle": true,
      "jsArguments": [],
      "paginationType": "NONE",
      "timeoutInMillisecond": 10000
    },
    "collectionId": "Company Documentation_ISOTags",
    "confirmBeforeExecute": false,
    "datasource": {
      "isAutoGenerated": false,
      "name": "UNUSED_DATASOURCE",
      "pluginId": "js-plugin"
    },
    "dynamicBindingPathList": [
      {
        "key": "body"
      }
    ],
    "fullyQualifiedName": "ISOTags.refresh",
    "name": "refresh",
    "pageId": "Company Documentation",
    "runBehaviour": "MANUAL",
    "userSetOnLoad": false
  }
}