{
  "gitSyncId": "6840b6d2ece888096e42342a_468c41fd-bcb8-49a5-ac9c-b101019b3ca1",
  "id": "Resources Original_get_membership_preview",
  "pluginId": "mysql-plugin",
  "pluginType": "DB",
  "unpublishedAction": {
    "actionConfiguration": {
      "body": "SELECT\n  r.resource_id,\n  r.resource_full_name,\n  CASE WHEN COALESCE(wtm.work_team_member_id, 0) = 0 THEN 0 ELSE 1 END AS already_in_team\nFROM resources r\nLEFT JOIN work_team_members wtm\n  ON wtm.resource_id = r.resource_id\n AND wtm.work_team_id = {{ i_wt_pick.selectedOptionValue || 0 }}\nWHERE r.resource_id IN (\n  {{ (tbl_resources.selectedRows || []).map(x => x.resource_id).join(',') || '0' }}\n);\n",
      "encodeParamsToggle": true,
      "paginationType": "NONE",
      "pluginSpecifiedTemplates": [
        {
          "value": false
        }
      ],
      "timeoutInMillisecond": 10000
    },
    "confirmBeforeExecute": false,
    "datasource": {
      "id": "linktranslation",
      "isAutoGenerated": false,
      "name": "linktranslation",
      "pluginId": "mysql-plugin"
    },
    "dynamicBindingPathList": [
      {
        "key": "body"
      }
    ],
    "name": "get_membership_preview",
    "pageId": "Resources Original",
    "runBehaviour": "MANUAL",
    "userSetOnLoad": false
  }
}