{
  "animateLoading": true,
  "borderRadius": "{{appsmith.theme.borderRadius.appBorderRadius}}",
  "bottomRow": 161,
  "dynamicBindingPathList": [
    {
      "key": "truncateButtonColor"
    },
    {
      "key": "fontFamily"
    },
    {
      "key": "borderRadius"
    },
    {
      "key": "text"
    }
  ],
  "dynamicHeight": "AUTO_HEIGHT",
  "dynamicTriggerPathList": [],
  "fontFamily": "{{appsmith.theme.fontFamily.appFont}}",
  "fontSize": "1rem",
  "fontStyle": "BOLD",
  "isLoading": false,
  "isVisible": false,
  "key": "d24hxovpf3",
  "leftColumn": 7,
  "maxDynamicHeight": 9000,
  "minDynamicHeight": 4,
  "minWidth": 450,
  "mobileBottomRow": 33,
  "mobileLeftColumn": 0,
  "mobileRightColumn": 11,
  "mobileTopRow": 29,
  "needsErrorInfo": false,
  "originalBottomRow": 23,
  "originalTopRow": 19,
  "overflow": "NONE",
  "parentColumnSpace": 27.703125,
  "parentId": "0",
  "parentRowSpace": 10,
  "renderMode": "CANVAS",
  "responsiveBehavior": "fill",
  "rightColumn": 10,
  "shouldTruncate": false,
  "text": "{{ Perms.init() }}\n",
  "textAlign": "LEFT",
  "textColor": "#231F20",
  "topRow": 157,
  "truncateButtonColor": "{{appsmith.theme.colors.primaryColor}}",
  "type": "TEXT_WIDGET",
  "version": 1,
  "widgetId": "g4rzrbqzc5",
  "widgetName": "txt_perm_init"
}