{
  "gitSyncId": "6840b6d2ece888096e42342a_d9868436-e535-4b01-822c-3aa55527a09f",
  "id": "Customers_get_currencies_dropdown",
  "pluginId": "mysql-plugin",
  "pluginType": "DB",
  "unpublishedAction": {
    "actionConfiguration": {
      "body": "SELECT currency_id AS value, currency_name AS label\nFROM currencies\nORDER BY currency_name;\n",
      "encodeParamsToggle": true,
      "paginationType": "NONE",
      "pluginSpecifiedTemplates": [
        {
          "value": true
        }
      ],
      "timeoutInMillisecond": 10000
    },
    "confirmBeforeExecute": false,
    "datasource": {
      "id": "linktranslation",
      "isAutoGenerated": false,
      "name": "linktranslation",
      "pluginId": "mysql-plugin"
    },
    "dynamicBindingPathList": [],
    "name": "get_currencies_dropdown",
    "pageId": "Customers",
    "runBehaviour": "AUTOMATIC",
    "userSetOnLoad": false
  }
}