{
  "gitSyncId": "6840b6d2ece888096e42342a_37437f42-2160-4db6-9fce-cb5be94a1b94",
  "id": "Resource Bills_get_last_inserted_bill_id",
  "pluginId": "mysql-plugin",
  "pluginType": "DB",
  "unpublishedAction": {
    "actionConfiguration": {
      "body": "SELECT LAST_INSERT_ID() AS last_bill_id;",
      "encodeParamsToggle": true,
      "paginationType": "NONE",
      "pluginSpecifiedTemplates": [
        {
          "value": true
        }
      ],
      "timeoutInMillisecond": 10000
    },
    "confirmBeforeExecute": false,
    "datasource": {
      "id": "linktranslation",
      "isAutoGenerated": false,
      "name": "linktranslation",
      "pluginId": "mysql-plugin"
    },
    "dynamicBindingPathList": [],
    "name": "get_last_inserted_bill_id",
    "pageId": "Resource Bills",
    "runBehaviour": "MANUAL",
    "userSetOnLoad": false
  }
}