{
  "accentColor": "{{appsmith.theme.colors.primaryColor}}",
  "animateLoading": true,
  "borderColor": "#93c5fd",
  "borderRadius": "1.5rem",
  "borderWidth": "3",
  "bottomRow": 134,
  "boxShadow": "{{appsmith.theme.boxShadow.appBoxShadow}}",
  "cachedTableData": {},
  "canFreezeColumn": true,
  "childStylesheet": {
    "button": {
      "borderRadius": "{{appsmith.theme.borderRadius.appBorderRadius}}",
      "boxShadow": "none",
      "buttonColor": "{{appsmith.theme.colors.primaryColor}}"
    },
    "editActions": {
      "discardBorderRadius": "{{appsmith.theme.borderRadius.appBorderRadius}}",
      "discardButtonColor": "{{appsmith.theme.colors.primaryColor}}",
      "saveBorderRadius": "{{appsmith.theme.borderRadius.appBorderRadius}}",
      "saveButtonColor": "{{appsmith.theme.colors.primaryColor}}"
    },
    "iconButton": {
      "borderRadius": "{{appsmith.theme.borderRadius.appBorderRadius}}",
      "boxShadow": "none",
      "buttonColor": "{{appsmith.theme.colors.primaryColor}}"
    },
    "menuButton": {
      "borderRadius": "{{appsmith.theme.borderRadius.appBorderRadius}}",
      "boxShadow": "none",
      "menuColor": "{{appsmith.theme.colors.primaryColor}}"
    }
  },
  "columnOrder": [
    "Initial_contact",
    "Last_contact",
    "Next_contact"
  ],
  "columnUpdatedAt": 1758577278307,
  "columnWidthMap": {},
  "customIsLoading": false,
  "customIsLoadingValue": "",
  "defaultPageSize": 0,
  "defaultSelectedRowIndex": 0,
  "defaultSelectedRowIndices": [
    0
  ],
  "delimiter": ",",
  "dynamicBindingPathList": [
    {
      "key": "accentColor"
    },
    {
      "key": "boxShadow"
    },
    {
      "key": "tableData"
    },
    {
      "key": "primaryColumns.Initial_contact.computedValue"
    },
    {
      "key": "primaryColumns.Last_contact.computedValue"
    },
    {
      "key": "primaryColumns.Next_contact.computedValue"
    }
  ],
  "dynamicPropertyPathList": [
    {
      "key": "tableData"
    }
  ],
  "dynamicTriggerPathList": [],
  "enableClientSideSearch": true,
  "endOfData": false,
  "flexVerticalAlignment": "start",
  "horizontalAlignment": "LEFT",
  "inlineEditingSaveOption": "ROW_LEVEL",
  "isLoading": false,
  "isSortable": true,
  "isVisible": true,
  "isVisibleDownload": true,
  "isVisibleFilters": false,
  "isVisiblePagination": true,
  "isVisibleSearch": true,
  "key": "u8ellbv6kl",
  "label": "Data",
  "leftColumn": 0,
  "minWidth": 450,
  "mobileBottomRow": 134,
  "mobileLeftColumn": 2,
  "mobileRightColumn": 36,
  "mobileTopRow": 106,
  "needsErrorInfo": false,
  "originalBottomRow": 134,
  "originalTopRow": 106,
  "parentColumnSpace": 25.875,
  "parentId": "0",
  "parentRowSpace": 10,
  "primaryColumns": {
    "Initial_contact": {
      "alias": "Initial contact",
      "allowCellWrapping": false,
      "allowSameOptionsInNewRow": true,
      "columnType": "date",
      "computedValue": "{{(() => { const tableData = tbl_contact_sched.processedTableData || []; return tableData.length > 0 ? tableData.map((currentRow, currentIndex) => (currentRow[\"Initial contact\"])) : Initial contact })()}}",
      "currencyCode": "USD",
      "decimals": 0,
      "enableFilter": true,
      "enableSort": true,
      "horizontalAlignment": "LEFT",
      "id": "Initial_contact",
      "index": 0,
      "inputFormat": "YYYY-MM-DD",
      "isCellEditable": false,
      "isCellVisible": true,
      "isDerived": false,
      "isDisabled": false,
      "isDiscardVisible": true,
      "isEditable": false,
      "isSaveVisible": true,
      "isVisible": true,
      "label": "Initial contact",
      "notation": "standard",
      "originalId": "Initial contact",
      "outputFormat": "YYYY-MM-DD",
      "sticky": "",
      "textSize": "0.875rem",
      "thousandSeparator": true,
      "validation": {},
      "verticalAlignment": "CENTER",
      "width": 150
    },
    "Last_contact": {
      "alias": "Last contact",
      "allowCellWrapping": false,
      "allowSameOptionsInNewRow": true,
      "columnType": "date",
      "computedValue": "{{(() => { const tableData = tbl_contact_sched.processedTableData || []; return tableData.length > 0 ? tableData.map((currentRow, currentIndex) => (currentRow[\"Last contact\"])) : Last contact })()}}",
      "currencyCode": "USD",
      "decimals": 0,
      "enableFilter": true,
      "enableSort": true,
      "horizontalAlignment": "LEFT",
      "id": "Last_contact",
      "index": 1,
      "inputFormat": "YYYY-MM-DD",
      "isCellEditable": false,
      "isCellVisible": true,
      "isDerived": false,
      "isDisabled": false,
      "isDiscardVisible": true,
      "isEditable": false,
      "isSaveVisible": true,
      "isVisible": true,
      "label": "Last contact",
      "notation": "standard",
      "originalId": "Last contact",
      "outputFormat": "YYYY-MM-DD",
      "sticky": "",
      "textSize": "0.875rem",
      "thousandSeparator": true,
      "validation": {},
      "verticalAlignment": "CENTER",
      "width": 150
    },
    "Next_contact": {
      "alias": "Next contact",
      "allowCellWrapping": false,
      "allowSameOptionsInNewRow": true,
      "columnType": "date",
      "computedValue": "{{(() => { const tableData = tbl_contact_sched.processedTableData || []; return tableData.length > 0 ? tableData.map((currentRow, currentIndex) => (currentRow[\"Next contact\"])) : Next contact })()}}",
      "currencyCode": "USD",
      "decimals": 0,
      "enableFilter": true,
      "enableSort": true,
      "horizontalAlignment": "LEFT",
      "id": "Next_contact",
      "index": 2,
      "inputFormat": "YYYY-MM-DD",
      "isCellEditable": false,
      "isCellVisible": true,
      "isDerived": false,
      "isDisabled": false,
      "isDiscardVisible": true,
      "isEditable": false,
      "isSaveVisible": true,
      "isVisible": true,
      "label": "Next contact",
      "notation": "standard",
      "originalId": "Next contact",
      "outputFormat": "YYYY-MM-DD",
      "sticky": "",
      "textSize": "0.875rem",
      "thousandSeparator": true,
      "validation": {},
      "verticalAlignment": "CENTER",
      "width": 150
    }
  },
  "renderMode": "CANVAS",
  "responsiveBehavior": "fill",
  "rightColumn": 30,
  "searchKey": "",
  "tableData": "{{\n  (get_contact_sched_byct.data || []).map(r => ({\n    'Initial contact': r.initial_contact || null,\n    'Last contact': r.last_contact || null,\n    'Next contact': r.next_contact || null\n  }))\n}}\n\n",
  "textSize": "0.875rem",
  "topRow": 106,
  "totalRecordsCount": 0,
  "type": "TABLE_WIDGET_V2",
  "variant": "VARIANT2",
  "version": 2,
  "verticalAlignment": "CENTER",
  "widgetId": "u6h9lbelqd",
  "widgetName": "tbl_contact_sched"
}