{
  "gitSyncId": "6840b6d2ece888096e42342a_ed71a3d9-7dfc-436e-bf79-318b61bd2758",
  "id": "Home_dbg_menu_vs_pages",
  "pluginId": "mysql-plugin",
  "pluginType": "DB",
  "unpublishedAction": {
    "actionConfiguration": {
      "body": "SELECT\n  ami.page_value\nFROM app_menu_items ami\nWHERE COALESCE(ami.is_active, 1) = 1\nORDER BY ami.page_value;\n",
      "encodeParamsToggle": true,
      "paginationType": "NONE",
      "pluginSpecifiedTemplates": [
        {
          "value": true
        }
      ],
      "timeoutInMillisecond": 10000
    },
    "confirmBeforeExecute": false,
    "datasource": {
      "id": "linktranslation",
      "isAutoGenerated": false,
      "name": "linktranslation",
      "pluginId": "mysql-plugin"
    },
    "dynamicBindingPathList": [],
    "name": "dbg_menu_vs_pages",
    "pageId": "Home",
    "runBehaviour": "MANUAL",
    "userSetOnLoad": false
  }
}