{
  "gitSyncId": "6840b6d2ece888096e42342a_0eef52ec-9d92-4e67-903d-53764c157ebc",
  "id": "NoAccess_Perms.has",
  "pluginId": "js-plugin",
  "pluginType": "JS",
  "unpublishedAction": {
    "actionConfiguration": {
      "encodeParamsToggle": true,
      "jsArguments": [
        {
          "name": "permKey"
        }
      ],
      "paginationType": "NONE",
      "timeoutInMillisecond": 10000
    },
    "collectionId": "NoAccess_Perms",
    "confirmBeforeExecute": false,
    "datasource": {
      "isAutoGenerated": false,
      "name": "UNUSED_DATASOURCE",
      "pluginId": "js-plugin"
    },
    "dynamicBindingPathList": [
      {
        "key": "body"
      }
    ],
    "fullyQualifiedName": "Perms.has",
    "name": "has",
    "pageId": "NoAccess",
    "runBehaviour": "MANUAL",
    "userSetOnLoad": false
  }
}