{
  "gitSyncId": "6840b6d2ece888096e42342a_4273f85f-7119-4b2e-b2ca-627ed8bfb2ae",
  "id": "Resource Banking_InsertBankingHandler.save",
  "pluginId": "js-plugin",
  "pluginType": "JS",
  "unpublishedAction": {
    "actionConfiguration": {
      "encodeParamsToggle": true,
      "jsArguments": [
        {
          "name": "form"
        }
      ],
      "paginationType": "NONE",
      "timeoutInMillisecond": 10000
    },
    "collectionId": "Resource Banking_InsertBankingHandler",
    "confirmBeforeExecute": false,
    "datasource": {
      "isAutoGenerated": false,
      "name": "UNUSED_DATASOURCE",
      "pluginId": "js-plugin"
    },
    "dynamicBindingPathList": [
      {
        "key": "body"
      }
    ],
    "fullyQualifiedName": "InsertBankingHandler.save",
    "name": "save",
    "pageId": "Resource Banking",
    "runBehaviour": "MANUAL",
    "userSetOnLoad": false
  }
}