{
  "gitSyncId": "6840b6d2ece888096e42342a_cca71409-6019-4827-b611-2a42126eb2d1",
  "id": "Projects_ProjFilter.field",
  "pluginId": "js-plugin",
  "pluginType": "JS",
  "unpublishedAction": {
    "actionConfiguration": {
      "encodeParamsToggle": true,
      "jsArguments": [],
      "paginationType": "NONE",
      "timeoutInMillisecond": 10000
    },
    "collectionId": "Projects_ProjFilter",
    "confirmBeforeExecute": false,
    "datasource": {
      "isAutoGenerated": false,
      "name": "UNUSED_DATASOURCE",
      "pluginId": "js-plugin"
    },
    "dynamicBindingPathList": [
      {
        "key": "body"
      }
    ],
    "fullyQualifiedName": "ProjFilter.field",
    "name": "field",
    "pageId": "Projects",
    "runBehaviour": "MANUAL",
    "userSetOnLoad": false
  }
}