{
  "gitSyncId": "6840b6d2ece888096e42342a_dfb08b89-01a9-44d6-8113-19cbc3d237b3",
  "id": "Templates_get_tpl_types",
  "pluginId": "mysql-plugin",
  "pluginType": "DB",
  "unpublishedAction": {
    "actionConfiguration": {
      "body": "SELECT\n  ami.label AS label,\n  ami.label AS value\nFROM app_menu_items ami\nWHERE ami.is_active = 1\nORDER BY ami.sort_order, ami.label;\n",
      "encodeParamsToggle": true,
      "paginationType": "NONE",
      "pluginSpecifiedTemplates": [
        {
          "value": true
        }
      ],
      "timeoutInMillisecond": 10000
    },
    "confirmBeforeExecute": false,
    "datasource": {
      "id": "linktranslation",
      "isAutoGenerated": false,
      "name": "linktranslation",
      "pluginId": "mysql-plugin"
    },
    "dynamicBindingPathList": [],
    "name": "get_tpl_types",
    "pageId": "Templates",
    "runBehaviour": "AUTOMATIC",
    "userSetOnLoad": false
  }
}