{
  "gitSyncId": "6840b6d2ece888096e42342a_761f1ace-ab55-463a-920c-44bfbe895427",
  "id": "Price List Items_PLIForm.openForEdit",
  "pluginId": "js-plugin",
  "pluginType": "JS",
  "unpublishedAction": {
    "actionConfiguration": {
      "encodeParamsToggle": true,
      "jsArguments": [
        {
          "name": "row"
        }
      ],
      "paginationType": "NONE",
      "timeoutInMillisecond": 10000
    },
    "collectionId": "Price List Items_PLIForm",
    "confirmBeforeExecute": false,
    "datasource": {
      "isAutoGenerated": false,
      "name": "UNUSED_DATASOURCE",
      "pluginId": "js-plugin"
    },
    "dynamicBindingPathList": [
      {
        "key": "body"
      }
    ],
    "fullyQualifiedName": "PLIForm.openForEdit",
    "name": "openForEdit",
    "pageId": "Price List Items",
    "runBehaviour": "MANUAL",
    "userSetOnLoad": false
  }
}