{
  "gitSyncId": "6840b6d2ece888096e42342a_7da73634-50a2-46f8-8b08-440bb3029daa",
  "id": "Projects_j_total.resetInsert",
  "pluginId": "js-plugin",
  "pluginType": "JS",
  "unpublishedAction": {
    "actionConfiguration": {
      "encodeParamsToggle": true,
      "jsArguments": [],
      "paginationType": "NONE",
      "timeoutInMillisecond": 10000
    },
    "collectionId": "Projects_j_total",
    "confirmBeforeExecute": false,
    "datasource": {
      "isAutoGenerated": false,
      "name": "UNUSED_DATASOURCE",
      "pluginId": "js-plugin"
    },
    "dynamicBindingPathList": [
      {
        "key": "body"
      }
    ],
    "fullyQualifiedName": "j_total.resetInsert",
    "name": "resetInsert",
    "pageId": "Projects",
    "runBehaviour": "MANUAL",
    "userSetOnLoad": false
  }
}